Workbook

Sheet 01_评分总览
A1: 中国宏观评级｜评分总览
A2: 四支柱固定权重30／30／20／20。政策分衡量逆周期动作与改革方向；经济结果由前三支柱验证。本期数值留空。
A4: 信息截止日
A6: 支柱 | B6: 固定权重 | C6: 已核验权重 | D6: 覆盖率 | E6: 得分贡献 | F6: 已覆盖观察分 | G6: 状态
A7: 经济运行 | B7: 0.3 | C7: =SUMIFS('02_指标录入'!$J$8:$J$36,'02_指标录入'!$B$8:$B$36,A7,'02_指标录入'!$I$8:$I$36,">=1") | D7: =IFERROR(C7/B7,0) | E7: =SUMIF('02_指标录入'!$B$8:$B$36,A7,'02_指标录入'!$K$8:$K$36) | F7: =IF(C7=0,"",E7/C7) | G7: =IF(D7>=0.7,"可观察","不足")
A8: 增长动力 | B8: 0.3 | C8: =SUMIFS('02_指标录入'!$J$8:$J$36,'02_指标录入'!$B$8:$B$36,A8,'02_指标录入'!$I$8:$I$36,">=1") | D8: =IFERROR(C8/B8,0) | E8: =SUMIF('02_指标录入'!$B$8:$B$36,A8,'02_指标录入'!$K$8:$K$36) | F8: =IF(C8=0,"",E8/C8) | G8: =IF(D8>=0.7,"可观察","不足")
A9: 金融信贷 | B9: 0.2 | C9: =SUMIFS('02_指标录入'!$J$8:$J$36,'02_指标录入'!$B$8:$B$36,A9,'02_指标录入'!$I$8:$I$36,">=1") | D9: =IFERROR(C9/B9,0) | E9: =SUMIF('02_指标录入'!$B$8:$B$36,A9,'02_指标录入'!$K$8:$K$36) | F9: =IF(C9=0,"",E9/C9) | G9: =IF(D9>=0.7,"可观察","不足")
A10: 宏观调控 | B10: 0.2 | C10: =SUMIFS('02_指标录入'!$J$8:$J$36,'02_指标录入'!$B$8:$B$36,A10,'02_指标录入'!$I$8:$I$36,">=1") | D10: =IFERROR(C10/B10,0) | E10: =SUMIF('02_指标录入'!$B$8:$B$36,A10,'02_指标录入'!$K$8:$K$36) | F10: =IF(C10=0,"",E10/C10) | G10: =IF(D10>=0.7,"可观察","不足")
A12: 四支柱合计 | B12: =SUM(B7:B10) | C12: =SUM(C7:C10) | D12: =IFERROR(C12/B12,0) | E12: =SUM(E7:E10) | F12: =IF(C12=0,"",E12/C12)
A14: 评级状态 | B14: =IF(ROUND(D12,6)=1,"正式",IF(AND(D12>=0.85,COUNTIF(G7:G10,"可观察")=4),"暂定","资料不足"))
A15: 正式总分 | B15: =IF(B14="正式",E12,"")
A16: 正式档位 | B16: =IF(B15="","不定正式档",IF(B15>=4.2,"I档 强复苏",IF(B15>=3.4,"II档 温和改善",IF(B15>=2.6,"III档 中性平稳",IF(B15>=1.8,"IV档 偏弱承压","V档 明显下行")))))
A18: 基本面观察分 | B18: =IF(SUM(C7:C9)=0,"",SUM(E7:E9)/SUM(C7:C9))
A19: 政策动作观察分 | B19: =F10
A21: 政策细分 | B21: 已覆盖观察分 | C21: 覆盖率
A22: 财政政策 | B22: =IFERROR(SUMIF('02_指标录入'!$C$8:$C$36,A22,'02_指标录入'!$K$8:$K$36)/SUMIFS('02_指标录入'!$J$8:$J$36,'02_指标录入'!$C$8:$C$36,A22,'02_指标录入'!$I$8:$I$36,">=1"),"") | C22: =IFERROR(SUMIFS('02_指标录入'!$J$8:$J$36,'02_指标录入'!$C$8:$C$36,A22,'02_指标录入'!$I$8:$I$36,">=1")/(0.2*0.3),0)
A23: 货币政策 | B23: =IFERROR(SUMIF('02_指标录入'!$C$8:$C$36,A23,'02_指标录入'!$K$8:$K$36)/SUMIFS('02_指标录入'!$J$8:$J$36,'02_指标录入'!$C$8:$C$36,A23,'02_指标录入'!$I$8:$I$36,">=1"),"") | C23: =IFERROR(SUMIFS('02_指标录入'!$J$8:$J$36,'02_指标录入'!$C$8:$C$36,A23,'02_指标录入'!$I$8:$I$36,">=1")/(0.2*0.3),0)
A24: 产业政策 | B24: =IFERROR(SUMIF('02_指标录入'!$C$8:$C$36,A24,'02_指标录入'!$K$8:$K$36)/SUMIFS('02_指标录入'!$J$8:$J$36,'02_指标录入'!$C$8:$C$36,A24,'02_指标录入'!$I$8:$I$36,">=1"),"") | C24: =IFERROR(SUMIFS('02_指标录入'!$J$8:$J$36,'02_指标录入'!$C$8:$C$36,A24,'02_指标录入'!$I$8:$I$36,">=1")/(0.2*0.2),0)
A25: 制度建设 | B25: =IFERROR(SUMIF('02_指标录入'!$C$8:$C$36,A25,'02_指标录入'!$K$8:$K$36)/SUMIFS('02_指标录入'!$J$8:$J$36,'02_指标录入'!$C$8:$C$36,A25,'02_指标录入'!$I$8:$I$36,">=1"),"") | C25: =IFERROR(SUMIFS('02_指标录入'!$J$8:$J$36,'02_指标录入'!$C$8:$C$36,A25,'02_指标录入'!$I$8:$I$36,">=1")/(0.2*0.2),0)
A28: 缺失项不补3分；观察分只描述已覆盖数据，完整覆盖才产生可比的正式分数。阈值是研究试行标准，不是官方评级。

Sheet 02_指标录入
A1: 本期指标录入
A2: 黄色格填统计期、发布日期、观测值、核验状态、官方链接与必要理由。原文评分从“政策原文依据”自动带入；不填本期数据就不生成评级。
A4: 源顺序：官方原始发布 → 万得 Wind → 财新数据 API；后两级仅在前级无法取得可核验数据时使用，并记录代码、原始机构、期数、单位和口径。
A7: ID | B7: 支柱 | C7: 类别 | D7: 核心指标 | E7: 统计期 | F7: 发布日期 | G7: 值／原文分 | H7: 核验 | I7: 得分 | J7: 固定权重 | K7: 得分贡献 | L7: 原文链接 | M7: 口径／评分理由
A8: E01 | B8: 经济运行 | C8: 经济增长 | D8: GDP同比增速（%） | H8: 待核验 | I8: =IF(OR(NOT(ISNUMBER(G8)),E8="",NOT(ISNUMBER(F8)),F8<=0,H8<>"已核验",L8="",NOT(ISNUMBER('01_评分总览'!$B$4)),F8>'01_评分总览'!$B$4),"",IF(G8<'03_评分标准'!O4,1,IF(G8<'03_评分标准'!P4,2,IF(G8<'03_评分标准'!Q4,3,IF(G8<'03_评分标准'!R4,4,5))))) | J8: ='03_评分标准'!H4 | K8: =IF(ISNUMBER(I8),I8*J8,0)
A9: E02 | B9: 经济运行 | C9: 物价水平 | D9: CPI同比（%） | H9: 待核验 | I9: =IF(OR(NOT(ISNUMBER(G9)),E9="",NOT(ISNUMBER(F9)),F9<=0,H9<>"已核验",L9="",NOT(ISNUMBER('01_评分总览'!$B$4)),F9>'01_评分总览'!$B$4),"",IF(AND(G9>='03_评分标准'!U5,G9<='03_评分标准'!V5),5,IF(AND(G9>='03_评分标准'!S5,G9<='03_评分标准'!T5),4,IF(AND(G9>='03_评分标准'!Q5,G9<='03_评分标准'!R5),3,IF(AND(G9>='03_评分标准'!O5,G9<='03_评分标准'!P5),2,1))))) | J9: ='03_评分标准'!H5 | K9: =IF(ISNUMBER(I9),I9*J9,0)
A10: E03 | B10: 经济运行 | C10: 物价水平 | D10: 核心CPI同比（%） | H10: 待核验 | I10: =IF(OR(NOT(ISNUMBER(G10)),E10="",NOT(ISNUMBER(F10)),F10<=0,H10<>"已核验",L10="",NOT(ISNUMBER('01_评分总览'!$B$4)),F10>'01_评分总览'!$B$4),"",IF(AND(G10>='03_评分标准'!U6,G10<='03_评分标准'!V6),5,IF(AND(G10>='03_评分标准'!S6,G10<='03_评分标准'!T6),4,IF(AND(G10>='03_评分标准'!Q6,G10<='03_评分标准'!R6),3,IF(AND(G10>='03_评分标准'!O6,G10<='03_评分标准'!P6),2,1))))) | J10: ='03_评分标准'!H6 | K10: =IF(ISNUMBER(I10),I10*J10,0)
A11: E04 | B11: 经济运行 | C11: 物价水平 | D11: PPI同比（%） | H11: 待核验 | I11: =IF(OR(NOT(ISNUMBER(G11)),E11="",NOT(ISNUMBER(F11)),F11<=0,H11<>"已核验",L11="",NOT(ISNUMBER('01_评分总览'!$B$4)),F11>'01_评分总览'!$B$4),"",IF(AND(G11>='03_评分标准'!U7,G11<='03_评分标准'!V7),5,IF(AND(G11>='03_评分标准'!S7,G11<='03_评分标准'!T7),4,IF(AND(G11>='03_评分标准'!Q7,G11<='03_评分标准'!R7),3,IF(AND(G11>='03_评分标准'!O7,G11<='03_评分标准'!P7),2,1))))) | J11: ='03_评分标准'!H7 | K11: =IF(ISNUMBER(I11),I11*J11,0)
A12: E05 | B12: 经济运行 | C12: 就业市场 | D12: 城镇调查失业率（%） | H12: 待核验 | I12: =IF(OR(NOT(ISNUMBER(G12)),E12="",NOT(ISNUMBER(F12)),F12<=0,H12<>"已核验",L12="",NOT(ISNUMBER('01_评分总览'!$B$4)),F12>'01_评分总览'!$B$4),"",IF(G12<'03_评分标准'!O8,5,IF(G12<'03_评分标准'!P8,4,IF(G12<'03_评分标准'!Q8,3,IF(G12<'03_评分标准'!R8,2,1))))) | J12: ='03_评分标准'!H8 | K12: =IF(ISNUMBER(I12),I12*J12,0)
A13: E06 | B13: 经济运行 | C13: 景气指数 | D13: 综合PMI产出指数 | H13: 待核验 | I13: =IF(OR(NOT(ISNUMBER(G13)),E13="",NOT(ISNUMBER(F13)),F13<=0,H13<>"已核验",L13="",NOT(ISNUMBER('01_评分总览'!$B$4)),F13>'01_评分总览'!$B$4),"",IF(G13<'03_评分标准'!O9,1,IF(G13<'03_评分标准'!P9,2,IF(G13<'03_评分标准'!Q9,3,IF(G13<'03_评分标准'!R9,4,5))))) | J13: ='03_评分标准'!H9 | K13: =IF(ISNUMBER(I13),I13*J13,0)
A14: G01 | B14: 增长动力 | C14: 工业生产 | D14: 规模以上工业增加值增速（%） | H14: 待核验 | I14: =IF(OR(NOT(ISNUMBER(G14)),E14="",NOT(ISNUMBER(F14)),F14<=0,H14<>"已核验",L14="",NOT(ISNUMBER('01_评分总览'!$B$4)),F14>'01_评分总览'!$B$4),"",IF(G14<'03_评分标准'!O10,1,IF(G14<'03_评分标准'!P10,2,IF(G14<'03_评分标准'!Q10,3,IF(G14<'03_评分标准'!R10,4,5))))) | J14: ='03_评分标准'!H10 | K14: =IF(ISNUMBER(I14),I14*J14,0)
A15: G02 | B15: 增长动力 | C15: 工业生产 | D15: 工业企业利润总额增速（%） | H15: 待核验 | I15: =IF(OR(NOT(ISNUMBER(G15)),E15="",NOT(ISNUMBER(F15)),F15<=0,H15<>"已核验",L15="",NOT(ISNUMBER('01_评分总览'!$B$4)),F15>'01_评分总览'!$B$4),"",IF(G15<'03_评分标准'!O11,1,IF(G15<'03_评分标准'!P11,2,IF(G15<'03_评分标准'!Q11,3,IF(G15<'03_评分标准'!R11,4,5))))) | J15: ='03_评分标准'!H11 | K15: =IF(ISNUMBER(I15),I15*J15,0)
A16: G03 | B16: 增长动力 | C16: 房地产 | D16: 商品房销售面积增速（%） | H16: 待核验 | I16: =IF(OR(NOT(ISNUMBER(G16)),E16="",NOT(ISNUMBER(F16)),F16<=0,H16<>"已核验",L16="",NOT(ISNUMBER('01_评分总览'!$B$4)),F16>'01_评分总览'!$B$4),"",IF(G16<'03_评分标准'!O12,1,IF(G16<'03_评分标准'!P12,2,IF(G16<'03_评分标准'!Q12,3,IF(G16<'03_评分标准'!R12,4,5))))) | J16: ='03_评分标准'!H12 | K16: =IF(ISNUMBER(I16),I16*J16,0)
A17: G04 | B17: 增长动力 | C17: 房地产 | D17: 房屋新开工面积增速（%） | H17: 待核验 | I17: =IF(OR(NOT(ISNUMBER(G17)),E17="",NOT(ISNUMBER(F17)),F17<=0,H17<>"已核验",L17="",NOT(ISNUMBER('01_评分总览'!$B$4)),F17>'01_评分总览'!$B$4),"",IF(G17<'03_评分标准'!O13,1,IF(G17<'03_评分标准'!P13,2,IF(G17<'03_评分标准'!Q13,3,IF(G17<'03_评分标准'!R13,4,5))))) | J17: ='03_评分标准'!H13 | K17: =IF(ISNUMBER(I17),I17*J17,0)
A18: G05 | B18: 增长动力 | C18: 房地产 | D18: 房地产开发企业资金来源增速（%） | H18: 待核验 | I18: =IF(OR(NOT(ISNUMBER(G18)),E18="",NOT(ISNUMBER(F18)),F18<=0,H18<>"已核验",L18="",NOT(ISNUMBER('01_评分总览'!$B$4)),F18>'01_评分总览'!$B$4),"",IF(G18<'03_评分标准'!O14,1,IF(G18<'03_评分标准'!P14,2,IF(G18<'03_评分标准'!Q14,3,IF(G18<'03_评分标准'!R14,4,5))))) | J18: ='03_评分标准'!H14 | K18: =IF(ISNUMBER(I18),I18*J18,0)
A19: G06 | B19: 增长动力 | C19: 投资 | D19: 固定资产投资（FAI）增速（%） | H19: 待核验 | I19: =IF(OR(NOT(ISNUMBER(G19)),E19="",NOT(ISNUMBER(F19)),F19<=0,H19<>"已核验",L19="",NOT(ISNUMBER('01_评分总览'!$B$4)),F19>'01_评分总览'!$B$4),"",IF(G19<'03_评分标准'!O15,1,IF(G19<'03_评分标准'!P15,2,IF(G19<'03_评分标准'!Q15,3,IF(G19<'03_评分标准'!R15,4,5))))) | J19: ='03_评分标准'!H15 | K19: =IF(ISNUMBER(I19),I19*J19,0)
A20: G07 | B20: 增长动力 | C20: 投资 | D20: 制造业投资增速（%） | H20: 待核验 | I20: =IF(OR(NOT(ISNUMBER(G20)),E20="",NOT(ISNUMBER(F20)),F20<=0,H20<>"已核验",L20="",NOT(ISNUMBER('01_评分总览'!$B$4)),F20>'01_评分总览'!$B$4),"",IF(G20<'03_评分标准'!O16,1,IF(G20<'03_评分标准'!P16,2,IF(G20<'03_评分标准'!Q16,3,IF(G20<'03_评分标准'!R16,4,5))))) | J20: ='03_评分标准'!H16 | K20: =IF(ISNUMBER(I20),I20*J20,0)
A21: G08 | B21: 增长动力 | C21: 投资 | D21: 民间固定资产投资增速（%） | H21: 待核验 | I21: =IF(OR(NOT(ISNUMBER(G21)),E21="",NOT(ISNUMBER(F21)),F21<=0,H21<>"已核验",L21="",NOT(ISNUMBER('01_评分总览'!$B$4)),F21>'01_评分总览'!$B$4),"",IF(G21<'03_评分标准'!O17,1,IF(G21<'03_评分标准'!P17,2,IF(G21<'03_评分标准'!Q17,3,IF(G21<'03_评分标准'!R17,4,5))))) | J21: ='03_评分标准'!H17 | K21: =IF(ISNUMBER(I21),I21*J21,0)
A22: G09 | B22: 增长动力 | C22: 消费 | D22: 社会消费品零售总额增速（%） | H22: 待核验 | I22: =IF(OR(NOT(ISNUMBER(G22)),E22="",NOT(ISNUMBER(F22)),F22<=0,H22<>"已核验",L22="",NOT(ISNUMBER('01_评分总览'!$B$4)),F22>'01_评分总览'!$B$4),"",IF(G22<'03_评分标准'!O18,1,IF(G22<'03_评分标准'!P18,2,IF(G22<'03_评分标准'!Q18,3,IF(G22<'03_评分标准'!R18,4,5))))) | J22: ='03_评分标准'!H18 | K22: =IF(ISNUMBER(I22),I22*J22,0)
A23: G10 | B23: 增长动力 | C23: 进出口 | D23: 出口金额增速（美元计，%） | H23: 待核验 | I23: =IF(OR(NOT(ISNUMBER(G23)),E23="",NOT(ISNUMBER(F23)),F23<=0,H23<>"已核验",L23="",NOT(ISNUMBER('01_评分总览'!$B$4)),F23>'01_评分总览'!$B$4),"",IF(G23<'03_评分标准'!O19,1,IF(G23<'03_评分标准'!P19,2,IF(G23<'03_评分标准'!Q19,3,IF(G23<'03_评分标准'!R19,4,5))))) | J23: ='03_评分标准'!H19 | K23: =IF(ISNUMBER(I23),I23*J23,0)
A24: F01 | B24: 金融信贷 | C24: 信贷结构 | D24: 居民中长期贷款近3月同比多增（亿元） | H24: 待核验 | I24: =IF(OR(NOT(ISNUMBER(G24)),E24="",NOT(ISNUMBER(F24)),F24<=0,H24<>"已核验",L24="",NOT(ISNUMBER('01_评分总览'!$B$4)),F24>'01_评分总览'!$B$4),"",IF(G24<'03_评分标准'!O20,1,IF(G24<'03_评分标准'!P20,2,IF(G24<'03_评分标准'!Q20,3,IF(G24<'03_评分标准'!R20,4,5))))) | J24: ='03_评分标准'!H20 | K24: =IF(ISNUMBER(I24),I24*J24,0)
... A27: F04 | B27: 金融信贷 | C27: 社会融资 | D27: 人民币贷款存量增速（%） | H27: 待核验 | I27: =IF(OR(NOT(ISNUMBER(G27)),E27="",NOT(ISNUMBER(F27)),F27<=0,H27<>"已核验",L27="",NOT(ISNUMBER('01_评分总览'!$B$4)),F27>'01_评分总览'!$B$4),"",IF(G27<'03_评分标准'!O23,1,IF(G27<'03_评分标准'!P23,2,IF(G27<'03_评分标准'!Q23,3,IF(G27<'03_评分标准'!R23,4,5))))) | J27: ='03_评分标准'!H23 | K27: =IF(ISNUMBER(I27),I27*J27,0)
A28: F05 | B28: 金融信贷 | C28: 货币供给 | D28: M1-M2剪刀差 | H28: 待核验 | I28: =IF(OR(NOT(ISNUMBER(G28)),E28="",NOT(ISNUMBER(F28)),F28<=0,H28<>"已核验",L28="",NOT(ISNUMBER('01_评分总览'!$B$4)),F28>'01_评分总览'!$B$4),"",IF(AND(G28>='03_评分标准'!U24,G28<='03_评分标准'!V24),5,IF(AND(G28>='03_评分标准'!S24,G28<='03_评分标准'!T24),4,IF(AND(G28>='03_评分标准'!Q24,G28<='03_评分标准'!R24),3,IF(AND(G28>='03_评分标准'!O24,G28<='03_评分标准'!P24),2,1))))) | J28: ='03_评分标准'!H24 | K28: =IF(ISNUMBER(I28),I28*J28,0)
A29: P01A | B29: 宏观调控 | C29: 财政政策 | D29: 新增财政融资工具占GDP比重同比变动 | H29: 待核验 | I29: =IF(OR(NOT(ISNUMBER(G29)),E29="",NOT(ISNUMBER(F29)),F29<=0,H29<>"已核验",L29="",NOT(ISNUMBER('01_评分总览'!$B$4)),F29>'01_评分总览'!$B$4),"",IF(G29<'03_评分标准'!O25,1,IF(G29<'03_评分标准'!P25,2,IF(G29<'03_评分标准'!Q25,3,IF(G29<'03_评分标准'!R25,4,5))))) | J29: ='03_评分标准'!H25 | K29: =IF(ISNUMBER(I29),I29*J29,0)
A30: P01B | B30: 宏观调控 | C30: 财政政策 | D30: 一般公共预算支出执行进度同比变动 | H30: 待核验 | I30: =IF(OR(NOT(ISNUMBER(G30)),E30="",NOT(ISNUMBER(F30)),F30<=0,H30<>"已核验",L30="",NOT(ISNUMBER('01_评分总览'!$B$4)),F30>'01_评分总览'!$B$4),"",IF(G30<'03_评分标准'!O26,1,IF(G30<'03_评分标准'!P26,2,IF(G30<'03_评分标准'!Q26,3,IF(G30<'03_评分标准'!R26,4,5))))) | J30: ='03_评分标准'!H26 | K30: =IF(ISNUMBER(I30),I30*J30,0)
A31: P01C | B31: 宏观调控 | C31: 财政政策 | D31: 新增地方专项债发行进度同比变动 | H31: 待核验 | I31: =IF(OR(NOT(ISNUMBER(G31)),E31="",NOT(ISNUMBER(F31)),F31<=0,H31<>"已核验",L31="",NOT(ISNUMBER('01_评分总览'!$B$4)),F31>'01_评分总览'!$B$4),"",IF(G31<'03_评分标准'!O27,1,IF(G31<'03_评分标准'!P27,2,IF(G31<'03_评分标准'!Q27,3,IF(G31<'03_评分标准'!R27,4,5))))) | J31: ='03_评分标准'!H27 | K31: =IF(ISNUMBER(I31),I31*J31,0)
A32: P02A | B32: 宏观调控 | C32: 货币政策 | D32: 7天逆回购政策利率近6个月变动 | H32: 待核验 | I32: =IF(OR(NOT(ISNUMBER(G32)),E32="",NOT(ISNUMBER(F32)),F32<=0,H32<>"已核验",L32="",NOT(ISNUMBER('01_评分总览'!$B$4)),F32>'01_评分总览'!$B$4),"",IF(G32<'03_评分标准'!O28,5,IF(G32<'03_评分标准'!P28,4,IF(G32<'03_评分标准'!Q28,3,IF(G32<'03_评分标准'!R28,2,1))))) | J32: ='03_评分标准'!H28 | K32: =IF(ISNUMBER(I32),I32*J32,0)
A33: P02B | B33: 宏观调控 | C33: 货币政策 | D33: 法定存款准备金率近6个月变动 | H33: 待核验 | I33: =IF(OR(NOT(ISNUMBER(G33)),E33="",NOT(ISNUMBER(F33)),F33<=0,H33<>"已核验",L33="",NOT(ISNUMBER('01_评分总览'!$B$4)),F33>'01_评分总览'!$B$4),"",IF(G33<'03_评分标准'!O29,5,IF(G33<'03_评分标准'!P29,4,IF(G33<'03_评分标准'!Q29,3,IF(G33<'03_评分标准'!R29,2,1))))) | J33: ='03_评分标准'!H29 | K33: =IF(ISNUMBER(I33),I33*J33,0)
A34: P02C | B34: 宏观调控 | C34: 货币政策 | D34: 结构性货币政策工具近3月净投放/GDP | H34: 待核验 | I34: =IF(OR(NOT(ISNUMBER(G34)),E34="",NOT(ISNUMBER(F34)),F34<=0,H34<>"已核验",L34="",NOT(ISNUMBER('01_评分总览'!$B$4)),F34>'01_评分总览'!$B$4),"",IF(G34<'03_评分标准'!O30,1,IF(G34<'03_评分标准'!P30,2,IF(G34<'03_评分标准'!Q30,3,IF(G34<'03_评分标准'!R30,4,5))))) | J34: ='03_评分标准'!H30 | K34: =IF(ISNUMBER(I34),I34*J34,0)
A35: P03 | B35: 宏观调控 | C35: 产业政策 | D35: 产业政策方向与工具 | E35: ='04_政策原文依据'!B5 | F35: ='04_政策原文依据'!C5 | G35: ='04_政策原文依据'!H5 | H35: ='04_政策原文依据'!I5 | I35: =IF(OR(NOT(ISNUMBER(G35)),E35="",NOT(ISNUMBER(F35)),F35<=0,H35<>"已核验",L35="",NOT(ISNUMBER('01_评分总览'!$B$4)),F35>'01_评分总览'!$B$4,'04_政策原文依据'!B5="",'04_政策原文依据'!C5="",'04_政策原文依据'!D5="",'04_政策原文依据'!E5="",'04_政策原文依据'!F5="",'04_政策原文依据'!G5="",G35<1,G35>5,MOD(G35,1)<>0),"",G35) | J35: ='03_评分标准'!H31 | K35: =IF(ISNUMBER(I35),I35*J35,0) | L35: ='04_政策原文依据'!D5 | M35: ='04_政策原文依据'!G5
A36: P04 | B36: 宏观调控 | C36: 制度建设 | D36: 制度建设方向与规则 | E36: ='04_政策原文依据'!B6 | F36: ='04_政策原文依据'!C6 | G36: ='04_政策原文依据'!H6 | H36: ='04_政策原文依据'!I6 | I36: =IF(OR(NOT(ISNUMBER(G36)),E36="",NOT(ISNUMBER(F36)),F36<=0,H36<>"已核验",L36="",NOT(ISNUMBER('01_评分总览'!$B$4)),F36>'01_评分总览'!$B$4,'04_政策原文依据'!B6="",'04_政策原文依据'!C6="",'04_政策原文依据'!D6="",'04_政策原文依据'!E6="",'04_政策原文依据'!F6="",'04_政策原文依据'!G6="",G36<1,G36>5,MOD(G36,1)<>0),"",G36) | J36: ='03_评分标准'!H32 | K36: =IF(ISNUMBER(I36),I36*J36,0) | L36: ='04_政策原文依据'!D6 | M36: ='04_政策原文依据'!G6

Sheet 03_评分标准
A1: 五档评分标准
A2: 一行一个核心指标；数字阈值和文本口径完整保留。财政、货币共六项量化规则；产业、制度沿用正式原文分档。隐藏的参数列只供自动计算。
A3: ID | B3: 支柱 | C3: 类别 | D3: 核心指标 | E3: 频率 | F3: 单位 | G3: 规则方向 | H3: 固定权重 | I3: 1分 | J3: 2分 | K3: 3分 | L3: 4分 | M3: 5分 | N3: 口径与边界
A4: E01 | B4: 经济运行 | C4: 经济增长 | D4: GDP同比增速（%） | E4: 季度 | F4: % | G4: 高优 | H4: 0.09 | I4: <3 % | J4: [3,4) % | K4: [4,5) % | L4: [5,6) % | M4: ≥6 % | N4: 不变价、当季/累计口径需固定；年度增长目标变化时重审阈值；初步核算及修订分开留档 | O4: 3 | P4: 4 | Q4: 5 | R4: 6
A5: E02 | B5: 经济运行 | C5: 物价水平 | D5: CPI同比（%） | E5: 月度 | F5: % | G5: 目标 | H5: 0.036 | I5: <0或>4.5 % | J5: 0～4.5 % | K5: 0.5～3.5 % | L5: 1～3 % | M5: 1.5～2.5 % | N5: 原发布口径；过低和过高都扣分；季节因素看环比辅助 | O5: 0 | P5: 4.5 | Q5: 0.5 | R5: 3.5 | S5: 1 | T5: 3 | U5: 1.5 | V5: 2.5
A6: E03 | B6: 经济运行 | C6: 物价水平 | D6: 核心CPI同比（%） | E6: 月度 | F6: % | G6: 目标 | H6: 0.03 | I6: <0或>4 % | J6: 0～4 % | K6: 0.5～3.5 % | L6: 1～3 % | M6: 1.5～2.5 % | N6: 原发布口径；扣除食品和能源，观察内需价格 | O6: 0 | P6: 4 | Q6: 0.5 | R6: 3.5 | S6: 1 | T6: 3 | U6: 1.5 | V6: 2.5
A7: E04 | B7: 经济运行 | C7: 物价水平 | D7: PPI同比（%） | E7: 月度 | F7: % | G7: 目标 | H7: 0.024 | I7: <-3或>8 % | J7: -3～8 % | K7: -2～6 % | L7: -1～4 % | M7: 0～3 % | N7: 原发布口径；极端高增可能来自成本冲击，不再机械给5分 | O7: -3 | P7: 8 | Q7: -2 | R7: 6 | S7: -1 | T7: 4 | U7: 0 | V7: 3
A8: E05 | B8: 经济运行 | C8: 就业市场 | D8: 城镇调查失业率（%） | E8: 月度 | F8: % | G8: 低优 | H8: 0.06 | I8: ≥6 % | J8: [5.5,6) % | K8: [5,5.5) % | L8: [4.5,5) % | M8: <4.5 % | N8: 原发布口径；配合就业质量、青年失业率观察；单一指标有限 | O8: 4.5 | P8: 5 | Q8: 5.5 | R8: 6
A9: E06 | B9: 经济运行 | C9: 景气指数 | D9: 综合PMI产出指数 | E9: 月度 | F9: 指数点 | G9: 高优 | H9: 0.06 | I9: <48 指数点 | J9: [48,50) 指数点 | K9: [50,52) 指数点 | L9: [52,54) 指数点 | M9: ≥54 指数点 | N9: 原发布口径；制造业和非制造业PMI保留作结构解释 | O9: 48 | P9: 50 | Q9: 52 | R9: 54
A10: G01 | B10: 增长动力 | C10: 工业生产 | D10: 规模以上工业增加值增速（%） | E10: 月度 | F10: % | G10: 高优 | H10: 0.036 | I10: <3 % | J10: [3,5) % | K10: [5,6) % | L10: [6,8) % | M10: ≥8 % | N10: 原发布口径；固定当月同比口径，1—2月合并发布 | O10: 3 | P10: 5 | Q10: 6 | R10: 8
A11: G02 | B11: 增长动力 | C11: 工业生产 | D11: 工业企业利润总额增速（%） | E11: 月度 | F11: % | G11: 高优 | H11: 0.024 | I11: <-10 % | J11: [-10,0) % | K11: [0,8) % | L11: [8,15) % | M11: ≥15 % | N11: 年初累计同比；官方多为年初累计同比，勿误写当月同比 | O11: -10 | P11: 0 | Q11: 8 | R11: 15
A12: G03 | B12: 增长动力 | C12: 房地产 | D12: 商品房销售面积增速（%） | E12: 月度 | F12: % | G12: 高优 | H12: 0.03 | I12: <-20 % | J12: [-20,-10) % | K12: [-10,0) % | L12: [0,5) % | M12: ≥5 % | N12: 年初累计同比；固定年初累计同比，不与单月增量混用 | O12: -20 | P12: -10 | Q12: 0 | R12: 5
A13: G04 | B13: 增长动力 | C13: 房地产 | D13: 房屋新开工面积增速（%） | E13: 月度 | F13: % | G13: 高优 | H13: 0.012 | I13: <-25 % | J13: [-25,-10) % | K13: [-10,0) % | L13: [0,10) % | M13: ≥10 % | N13: 年初累计同比；固定年初累计同比 | O13: -25 | P13: -10 | Q13: 0 | R13: 10
A14: G05 | B14: 增长动力 | C14: 房地产 | D14: 房地产开发企业资金来源增速（%） | E14: 月度 | F14: % | G14: 高优 | H14: 0.018 | I14: <-15 % | J14: [-15,-5) % | K14: [-5,0) % | L14: [0,10) % | M14: ≥10 % | N14: 年初累计同比；固定年初累计同比 | O14: -15 | P14: -5 | Q14: 0 | R14: 10
A15: G06 | B15: 增长动力 | C15: 投资 | D15: 固定资产投资（FAI）增速（%） | E15: 月度 | F15: % | G15: 高优 | H15: 0.015 | I15: <2 % | J15: [2,4) % | K15: [4,6) % | L15: [6,8) % | M15: ≥8 % | N15: 年初累计同比；不含农户；固定年初累计同比 | O15: 2 | P15: 4 | Q15: 6 | R15: 8
A16: G07 | B16: 增长动力 | C16: 投资 | D16: 制造业投资增速（%） | E16: 月度 | F16: % | G16: 高优 | H16: 0.03 | I16: <4 % | J16: [4,7) % | K16: [7,10) % | L16: [10,14) % | M16: ≥14 % | N16: 年初累计同比；不含农户；固定年初累计同比 | O16: 4 | P16: 7 | Q16: 10 | R16: 14
A17: G08 | B17: 增长动力 | C17: 投资 | D17: 民间固定资产投资增速（%） | E17: 月度 | F17: % | G17: 高优 | H17: 0.03 | I17: <2 % | J17: [2,4) % | K17: [4,6) % | L17: [6,9) % | M17: ≥9 % | N17: 年初累计同比；不含农户；固定年初累计同比 | O17: 2 | P17: 4 | Q17: 6 | R17: 9
A18: G09 | B18: 增长动力 | C18: 消费 | D18: 社会消费品零售总额增速（%） | E18: 月度 | F18: % | G18: 高优 | H18: 0.075 | I18: <2 % | J18: [2,4) % | K18: [4,6) % | L18: [6,8) % | M18: ≥8 % | N18: 当月名义同比；固定当月名义同比；服务零售辅助验证 | O18: 2 | P18: 4 | Q18: 6 | R18: 8
A19: G10 | B19: 增长动力 | C19: 进出口 | D19: 出口金额增速（美元计，%） | E19: 月度 | F19: % | G19: 高优 | H19: 0.03 | I19: <-5 % | J19: [-5,0) % | K19: [0,5) % | L19: [5,10) % | M19: ≥10 % | N19: 美元计当月同比；固定美元计同比；人民币计与价格拆分辅助 | O19: -5 | P19: 0 | Q19: 5 | R19: 10
... A23: F04 | B23: 金融信贷 | C23: 社会融资 | D23: 人民币贷款存量增速（%） | E23: 月度 | F23: % | G23: 高优 | H23: 0.03 | I23: <7 % | J23: [7,9) % | K23: [9,11) % | L23: [11,13) % | M23: ≥13 % | N23: 期末同比；与社融存量增速信息重叠，权重已下调；核清金融机构/社融口径 | O23: 7 | P23: 9 | Q23: 11 | R23: 13
A24: F05 | B24: 金融信贷 | C24: 货币供给 | D24: M1-M2剪刀差 | E24: 月度 | F24: 百分点 | G24: 目标 | H24: 0.05 | I24: <-10或>12 百分点 | J24: -10～12 百分点 | K24: -5～8 百分点 | L24: -2～5 百分点 | M24: 0～3 百分点 | N24: 新口径M1同比−同月M2同比；M1同比减M2同比；新旧M1口径不能直接连成同一评级序列 | O24: -10 | P24: 12 | Q24: -5 | R24: 8 | S24: -2 | T24: 5 | U24: 0 | V24: 3
A25: P01A | B25: 宏观调控 | C25: 财政政策 | D25: 新增财政融资工具占GDP比重同比变动 | E25: 年度预算／月度复核 | F25: 百分点 | G25: 高优 | H25: 0.024 | I25: <-1 百分点 | J25: [-1,-0.25) 百分点 | K25: [-0.25,0.25) 百分点 | L25: [0.25,1) 百分点 | M25: ≥1 百分点 | N25: 当年正式批准的赤字融资＋新增地方专项债＋特别国债等不重叠额度，除以上年已公布名义GDP；减上年额度/再上年GDP，避免用尚未公布的当年GDP；首选原始机构：全国人大、财政部 | O25: -1 | P25: -0.25 | Q25: 0.25 | R25: 1
A26: P01B | B26: 宏观调控 | C26: 财政政策 | D26: 一般公共预算支出执行进度同比变动 | E26: 月度 | F26: 百分点 | G26: 高优 | H26: 0.021 | I26: <-10 百分点 | J26: [-10,-3) 百分点 | K26: [-3,3) 百分点 | L26: [3,10) 百分点 | M26: ≥10 百分点 | N26: 截至本月累计支出/当年批准预算支出，减上年同月累计支出/上年批准预算支出；年初月度季节性单列说明；首选原始机构：财政部 | O26: -10 | P26: -3 | Q26: 3 | R26: 10
A27: P01C | B27: 宏观调控 | C27: 财政政策 | D27: 新增地方专项债发行进度同比变动 | E27: 月度 | F27: 百分点 | G27: 高优 | H27: 0.015 | I27: <-15 百分点 | J27: [-15,-5) 百分点 | K27: [-5,5) 百分点 | L27: [5,15) 百分点 | M27: ≥15 百分点 | N27: 截至本月新增专项债累计发行额/当年正式批准新增额度，减上年同月累计发行额/上年批准额度；不含再融资债；首选原始机构：财政部 | O27: -15 | P27: -5 | Q27: 5 | R27: 15
A28: P02A | B28: 宏观调控 | C28: 货币政策 | D28: 7天逆回购政策利率近6个月变动 | E28: 事件驱动／月度复核 | F28: 基点 | G28: 低优 | H28: 0.027 | I28: ≥30 基点 | J28: [10,30) 基点 | K28: [-10,10) 基点 | L28: [-30,-10) 基点 | M28: <-30 基点 | N28: 本期央行7天逆回购政策利率减6个月前同政策利率；已正式公布的调整计入，不用LPR或DR007替代；首选原始机构：中国人民银行 | O28: -30 | P28: -10 | Q28: 10 | R28: 30
A29: P02B | B29: 宏观调控 | C29: 货币政策 | D29: 法定存款准备金率近6个月变动 | E29: 事件驱动／月度复核 | F29: 基点 | G29: 低优 | H29: 0.021 | I29: ≥100 基点 | J29: [50,100) 基点 | K29: [-50,50) 基点 | L29: [-100,-50) 基点 | M29: <-100 基点 | N29: 本期与6个月前同类机构法定准备金率差；分档或定向调整须说明覆盖范围；正式核实未调整时填0；首选原始机构：中国人民银行 | O29: -100 | P29: -50 | Q29: 50 | R29: 100
A30: P02C | B30: 宏观调控 | C30: 货币政策 | D30: 结构性货币政策工具近3月净投放/GDP | E30: 月度 | F30: 占GDP百分比 | G30: 高优 | H30: 0.012 | I30: <-0.1 占GDP百分比 | J30: [-0.1,-0.025) 占GDP百分比 | K30: [-0.025,0.025) 占GDP百分比 | L30: [0.025,0.1) 占GDP百分比 | M30: ≥0.1 占GDP百分比 | N30: 央行每月披露的“其他结构性货币政策工具”近3月投放减回笼之和/最近四季名义GDP；核对工具更替和口径变化；首选原始机构：中国人民银行 | O30: -0.1 | P30: -0.025 | Q30: 0.025 | R30: 0.1
A31: P03 | B31: 宏观调控 | C31: 产业政策 | D31: 产业政策方向与工具 | E31: 事件驱动／月度复核 | F31: 1—5分 | G31: 原文研判 | H31: 0.04 | I31: 正式政策总体撤回支持或显著抑制有效供给/竞争 | J31: 政策方向偏约束，或支持范围极窄、缺乏具体工具 | K31: 有正式方向但无具体措施，或正负影响大体抵消 | L31: 正式细则、资源/试点/标准和适用范围明确 | M31: 跨部门政策组合、资金/标准/试点和时间表明确；无需等待订单兑现 | N31: 逐篇核对正式原文：政策方向、覆盖范围、工具/资源、明确时点；供给侧出清和新兴产业支持均可计入，但同时记录受益及受损行业。；首选原始机构：国务院、国家发展改革委、工业和信息化部等
A32: P04 | B32: 宏观调控 | C32: 制度建设 | D32: 制度建设方向与规则 | E32: 事件驱动／月度复核 | F32: 1—5分 | G32: 原文研判 | H32: 0.04 | I32: 正式制度变化显著削弱市场准入、产权或规则稳定性 | J32: 方向偏限制或不确定性增加，细则不足 | K32: 正式改革方向已提出但机制与生效安排不明，或正负影响抵消 | L32: 明确的法律/制度文本、实施细则和生效时点 | M32: 多项关键制度的规则、责任机构及落地时间表明确；无需等待企业盈利兑现 | N32: 逐篇核对法律法规、国务院/监管部门正式原文：市场准入、产权与竞争、要素配置、监管可预期性；记录时点和适用范围。；首选原始机构：全国人大、国务院及相关监管部门

Sheet 04_政策原文依据
A1: 产业政策与制度建设｜原文评分依据
A2: 只保留两个需要研判的政策类别。记录官方原文事实与研究判断，再按“评分标准”的五档规则填分；不等待增长或信贷效果兑现。
A4: 类别 | B4: 观察期 | C4: 发布日期 | D4: 官方原文链接 | E4: 官方事实摘录 | F4: 政策方向／覆盖范围 | G4: 评分理由与主要约束 | H4: 原文分（1—5） | I4: 核验状态 | J4: 相关投资观察（待验证）
A5: 产业政策 | I5: 待核验
A6: 制度建设 | I6: 待核验

Sheet 05_历史记录
A1: 历史评级快照
A2: 月度观察、季度定级后，将总览结果“粘贴为值”追加到新行；保留当时信息截止日与规则版本，不用修订后的数据覆盖旧评级。
A3: 类型 | B3: 信息截止日 | C3: 评价期 | D3: 规则版本 | E3: 经济运行 | F3: 增长动力 | G3: 金融信贷 | H3: 宏观调控 | I3: 正式总分 | J3: 正式档位 | K3: 覆盖率 | L3: 政策依据／分歧 | M3: 投研验证点
